{
  "manifest": {
    "publishingInformation": {
      "locales": {
        "en-US": {
          "summary": "Sample Short Description",
          "examplePhrases": [
            "Alexa open hello world",
            "hello",
            "help"
          ],
          "name": "TKOTriviaAlexa",
          "description": "Sample Full Description"
        }
      },
      "isAvailableWorldwide": true,
      "testingInstructions": "Sample Testing Instructions.",
      "category": "KNOWLEDGE_AND_TRIVIA",
      "distributionCountries": []
    },
    "apis": {
      "custom": {
        "endpoint": {
          "sourceDir": "lambda/custom",
          "uri": "TKOTriviaAlexa"
        },
        "interfaces": [
          {
            "type":"ALEXA_PRESENTATION_APL"
          } 
        ]
      }
    },
    "manifestVersion": "1.0"
  }
}
